vastpy/__init__.py
vastpy/cli.py
vastpy-0.3.20.dist-info/LICENSE
vastpy-0.3.20.dist-info/METADATA
vastpy-0.3.20.dist-info/WHEEL
vastpy-0.3.20.dist-info/entry_points.txt
vastpy-0.3.20.dist-info/RECORD
